AUTHORS
LICENSE
MANIFEST.in
README
setup.py
src/__init__.py
src/cli/__init__.py
src/cli/compat.py
src/cli/context.py
src/cli/error.py
src/cli/executionmode.py
src/cli/main.py
src/cli/messages.py
src/cli/object.py
src/cli/parser.py
src/cli/plyparse.py
src/cli/settings.py
src/cli/terminal.py
src/cli/warning.py
src/cli/command/__init__.py
src/cli/command/cd.py
src/cli/command/clear.py
src/cli/command/command.py
src/cli/command/exit.py
src/cli/command/help.py
src/cli/command/pwd.py
src/cli/command/save.py
src/cli/command/set.py
src/cli/command/status.py
src/cli/platform/__init__.py
src/cli/platform/posix/__init__.py
src/cli/platform/posix/terminal.py
src/cli/platform/posix/util.py
src/ovirt_shell.egg-info/PKG-INFO
src/ovirt_shell.egg-info/SOURCES.txt
src/ovirt_shell.egg-info/dependency_links.txt
src/ovirt_shell.egg-info/entry_points.txt
src/ovirt_shell.egg-info/requires.txt
src/ovirt_shell.egg-info/top_level.txt
src/ovirtcli/__init__.py
src/ovirtcli/main.py
src/ovirtcli/annotations/__init__.py
src/ovirtcli/annotations/requires.py
src/ovirtcli/annotations/singleton.py
src/ovirtcli/command/__init__.py
src/ovirtcli/command/action.py
src/ovirtcli/command/add.py
src/ovirtcli/command/capabilities.py
src/ovirtcli/command/command.py
src/ovirtcli/command/connect.py
src/ovirtcli/command/console.py
src/ovirtcli/command/disconnect.py
src/ovirtcli/command/getkey_cmd.py
src/ovirtcli/command/help.py
src/ovirtcli/command/history.py
src/ovirtcli/command/info.py
src/ovirtcli/command/list.py
src/ovirtcli/command/ping.py
src/ovirtcli/command/remove.py
src/ovirtcli/command/show.py
src/ovirtcli/command/status.py
src/ovirtcli/command/summary.py
src/ovirtcli/command/update.py
src/ovirtcli/events/__init__.py
src/ovirtcli/events/abstractevent.py
src/ovirtcli/events/event.py
src/ovirtcli/events/ievent.py
src/ovirtcli/format/__init__.py
src/ovirtcli/format/format.py
src/ovirtcli/format/help.py
src/ovirtcli/format/text.py
src/ovirtcli/format/xml_.py
src/ovirtcli/infrastructure/__init__.py
src/ovirtcli/infrastructure/context.py
src/ovirtcli/infrastructure/historymanager.py
src/ovirtcli/infrastructure/object.py
src/ovirtcli/infrastructure/options.py
src/ovirtcli/infrastructure/settings.py
src/ovirtcli/listeners/__init__.py
