Metadata-Version: 1.1
Name: ovirt-shell
Version: 3.6.2.0
Summary: A command-line interface to oVirt Virtualization
Home-page: http://www.ovirt.org/wiki/CLI
Author: Michael Pasternak
Author-email: mpastern@redhat.com
License: ASL2
Platform: UNKNOWN
Classifier: Development Status :: 4 - Beta
Classifier: Environment :: Console
Classifier: Intended Audience :: System Administrators
Classifier: License :: OSI Approved :: Apache Software License
Classifier: Operating System :: OS Independent
Classifier: Programming Language :: Python :: 2.4
